ap_games/__init__.py
ap_games/__main__.py
ap_games/ap_types.py
ap_games/cli.py
ap_games/config.ini
ap_games/log.py
ap_games/py.typed
ap_games/game/__init__.py
ap_games/game/game_base.py
ap_games/game/py.typed
ap_games/game/reversi.py
ap_games/game/tictactoe.py
ap_games/gameboard/__init__.py
ap_games/gameboard/gameboard.py
ap_games/gameboard/py.typed
ap_games/player/__init__.py
ap_games/player/ai_player.py
ap_games/player/human_player.py
ap_games/player/player.py
ap_games/player/py.typed
ap_games-0.0.2.dist-info/LICENSE.txt
ap_games-0.0.2.dist-info/METADATA
ap_games-0.0.2.dist-info/WHEEL
ap_games-0.0.2.dist-info/entry_points.txt
ap_games-0.0.2.dist-info/top_level.txt
ap_games-0.0.2.dist-info/RECORD
