Metadata-Version: 2.1
Name: ap-games
Version: 0.0.2
Summary: Games Tic-Tac-Toe and Reversi with CLI.
Home-page: https://github.com/aplatkouski/ap-games
Author: Artsiom Platkouski
Author-email: komukc.apt@gmail.com
License: MIT
Project-URL: Bug Reports, https://github.com/aplatkouski/ap-games/issues
Project-URL: Source, https://github.com/aplatkouski/ap-games
Keywords: board game,console game,tic-tac-toe,reversi
Platform: UNKNOWN
Classifier: Development Status :: 4 - Beta
Classifier: Environment :: Console
Classifier: Intended Audience :: Developers
Classifier: Intended Audience :: End Users/Desktop
Classifier: License :: OSI Approved :: MIT License
Classifier: Natural Language :: English
Classifier: Operating System :: OS Independent
Classifier: Programming Language :: Python
Classifier: Programming Language :: Python :: 3
Classifier: Programming Language :: Python :: 3 :: Only
Classifier: Programming Language :: Python :: 3.8
Classifier: Programming Language :: Python :: Implementation :: CPython
Classifier: Topic :: Games/Entertainment :: Board Games
Classifier: Topic :: Software Development :: Libraries :: Python Modules
Requires-Python: <4,>=3.8
Provides-Extra: dev
Requires-Dist: black (==19.10b0) ; extra == 'dev'
Requires-Dist: bump2version (==1.0.0) ; extra == 'dev'
Requires-Dist: check-manifest (==0.42) ; extra == 'dev'
Requires-Dist: darglint (==1.5.2) ; extra == 'dev'
Requires-Dist: flake8 (==3.8.3) ; extra == 'dev'
Requires-Dist: flake8-bugbear (==20.1.4) ; extra == 'dev'
Requires-Dist: flake8-builtins (==1.5.3) ; extra == 'dev'
Requires-Dist: flake8-docstrings (==1.5.0) ; extra == 'dev'
Requires-Dist: flake8-import-order (==0.18.1) ; extra == 'dev'
Requires-Dist: flake8-mypy (==17.8.0) ; extra == 'dev'
Requires-Dist: flake8-pytest-style (==1.2.3) ; extra == 'dev'
Requires-Dist: flake8-rst-docstrings (==0.0.13) ; extra == 'dev'
Requires-Dist: flake8-typing-imports (==1.9.0) ; extra == 'dev'
Requires-Dist: keyring (==21.3.0) ; extra == 'dev'
Requires-Dist: mypy (==0.782) ; extra == 'dev'
Requires-Dist: mypy-extensions (==0.4.3) ; extra == 'dev'
Requires-Dist: pre-commit (==2.6.0) ; extra == 'dev'
Requires-Dist: pre-commit-hooks (==3.2.0) ; extra == 'dev'
Requires-Dist: pydocstyle (==5.0.2) ; extra == 'dev'
Requires-Dist: pyupgrade (==2.7.2) ; extra == 'dev'
Requires-Dist: tox (==3.19.0) ; extra == 'dev'
Requires-Dist: twine (==3.2.0) ; extra == 'dev'
Provides-Extra: test
Requires-Dist: coverage (==5.2.1) ; extra == 'test'
Requires-Dist: pytest (==6.0.1) ; extra == 'test'
Requires-Dist: pytest-cov (==2.10.1) ; extra == 'test'
